{
  "Tasks": [
    {
      "id": 1,
      "title": "CTV Làm việc kho BEST KCN Tân Bình ca 15:00 - 23:00 - 27/03-02/04",
      "description": "Lorem Ipsum chỉ đơn giản là văn bản giả của ngành in ấn và sắp chữ. Lorem Ipsum đã trở thành văn bản giả tiêu chuẩn của ngành kể từ những năm 1500, khi một nhà in không xác định lấy một dãy loại và xáo trộn nó để tạo thành một cuốn sách mẫu. Nó đã tồn tại không chỉ năm thế kỷ, mà còn là bước nhảy vọt trong lĩnh vực sắp chữ điện tử, về cơ bản vẫn không thay đổi. Nó được phổ biến vào những năm 1960 với việc phát hành các tờ Letraset chứa các đoạn Lorem Ipsum, và gần đây hơn là với phần mềm xuất bản trên máy tính để bàn như Aldus PageMaker bao gồm các phiên bản của Lorem Ipsum.",
      "images": "https://thuthuatnhanh.com/wp-content/uploads/2018/07/anh-dai-dien-dep.jpg",
      "address": "Quận Bình Tân, Hồ Chí Minh",
      "createdAt": "2022-04-09T03:40:26.950Z",
      "timeofTask": "2022-04-09T03:40:26.950Z",
      "category": "Vận chuyển",
      "initialPrice": 300,
      "bidBy": [4],
      "requirement": [
        {
          "id": 1,
          "content": "Có sức khỏe"
        },
        {
          "id": 2,
          "content": "Có tiền"
        }
      ],
      "comment": [
        {
          "id": 1,
          "content": "Tôi muốn abc",
          "user_id": 1,
          "time": "11 giờ trước"
        },
        {
          "id": 2,
          "content": "Tôi muốn abc",
          "user_id": 4,
          "time": "11 giờ trước"
        }
      ],
      "Recruiter": 1,
      "ListUser": [
        {
          "id": 11,
          "id_user": 3,
          "title": " Giúp tôi với bạn ơi !!",
          "content": "Tôi muốn bạn chỉnh lại 1 chút về thù lao của công việc, nếu được ta sẽ làm việc với nhau nhé"
        },
        {
          "id": 12,
          "id_user": 2,
          "title": " Giúp tôi với bạn ơi !!",
          "content": "Cho tôi nhận công việc này nhé !!"
        }
      ],
      "Receiver": null,
      "status": "pending"
    },
    {
      "id": 2,
      "title": "Đóng gói vận chuyển đồ đạc",
      "description": "Lorem Ipsum chỉ đơn giản là văn bản giả của ngành in ấn và sắp chữ. Lorem Ipsum đã trở thành văn bản giả tiêu chuẩn của ngành kể từ những năm 1500, khi một nhà in không xác định lấy một dãy loại và xáo trộn nó để tạo thành một cuốn sách mẫu. Nó đã tồn tại không chỉ năm thế kỷ, mà còn là bước nhảy vọt trong lĩnh vực sắp chữ điện tử, về cơ bản vẫn không thay đổi. Nó được phổ biến vào những năm 1960 với việc phát hành các tờ Letraset chứa các đoạn Lorem Ipsum, và gần đây hơn là với phần mềm xuất bản trên máy tính để bàn như Aldus PageMaker bao gồm các phiên bản của Lorem Ipsum.",
      "images": "https://upanh123.com/wp-content/uploads/2021/04/anh-dai-dien-buon-cho-nam16.jpg",
      "address": "Hà Nội",
      "createdAt": "2022-04-09T03:40:26.950Z",
      "timeofTask": "2022-04-09T03:40:26.950Z",
      "category": "Lập trình & IT",
      "initialPrice": 300,
      "bidBy": [3],
      "requirement": [
        {
          "id": 1,
          "content": "Có sức khỏe"
        },
        {
          "id": 2,
          "content": "Có tiền"
        }
      ],
      "comment": [
        {
          "id": 1,
          "content": "Cho mình hỏi mình có thể đề xuất lại với nhau không ạ?",
          "user_id": 1,
          "time": "11 giờ trước"
        },
        {
          "id": 2,
          "content": "Tôi muốn abc",
          "user_id": 3,
          "time": "11 giờ trước"
        }
      ],
      "Recruiter": 1,
      "ListUser": [
        {
          "id": 1,
          "id_user": 3,
          "title": "Giúp tôi với bạn ơi1 !!",
          "content": "Tôi muốn bạn chỉnh lại 1 chút về thù lao của công việc, nếu được ta sẽ làm việc với nhau nhé"
        },
        {
          "id": 2,
          "id_user": 2,
          "title": " Giúp tôi với bạn ơi !!",
          "content": "Cho tôi nhận công việc này nhé !!"
        }
      ],
      "Receiver": null,
      "status": "pending"
    },
    {
      "id": 3,
      "title": "Hải Dương - Nhân Viên Kho (Làm Giờ Hành Chính Từ T2 đến T7)",
      "description": "Lorem Ipsum chỉ đơn giản là văn bản giả của ngành in ấn và sắp chữ. Lorem Ipsum đã trở thành văn bản giả tiêu chuẩn của ngành kể từ những năm 1500, khi một nhà in không xác định lấy một dãy loại và xáo trộn nó để tạo thành một cuốn sách mẫu. Nó đã tồn tại không chỉ năm thế kỷ, mà còn là bước nhảy vọt trong lĩnh vực sắp chữ điện tử, về cơ bản vẫn không thay đổi. Nó được phổ biến vào những năm 1960 với việc phát hành các tờ Letraset chứa các đoạn Lorem Ipsum, và gần đây hơn là với phần mềm xuất bản trên máy tính để bàn như Aldus PageMaker bao gồm các phiên bản của Lorem Ipsum.",
      "images": "https://haycafe.vn/wp-content/uploads/2021/12/anh-dai-dien-con-gai-view-cuc-chill.jpg",
      "address": "Hà Nội",
      "createdAt": "2022-04-09T03:40:26.950Z",
      "timeofTask": "2022-04-09T03:40:26.950Z",
      "category": "Dịch vụ",
      "initialPrice": 500,
      "bidBy": [5],
      "requirement": [
        {
          "id": 1,
          "content": "Có sức khỏe"
        }
      ],
      "comment": null,
      "Recruiter": 2,
      "ListUser": [
        {
          "id": 3,
          "id_user": 1,
          "title": " Giúp tôi với bạn ơi !!",
          "content": "Tôi muốn bạn chỉnh lại 1 chút về thù lao của công việc, nếu được ta sẽ làm việc với nhau nhé"
        },
        {
          "id": 4,
          "id_user": 4,
          "title": " Giúp tôi với bạn ơi !!",
          "content": "Cho tôi nhận công việc này nhé !!"
        }
      ],
      "Receiver": 2,
      "status": "working"
    },
    {
      "id": 4,
      "title": "IT Helpdesk - Hà Nội (Đi Làm Ngay)",
      "description": "Lorem Ipsum chỉ đơn giản là văn bản giả của ngành in ấn và sắp chữ. Lorem Ipsum đã trở thành văn bản giả tiêu chuẩn của ngành kể từ những năm 1500, khi một nhà in không xác định lấy một dãy loại và xáo trộn nó để tạo thành một cuốn sách mẫu. Nó đã tồn tại không chỉ năm thế kỷ, mà còn là bước nhảy vọt trong lĩnh vực sắp chữ điện tử, về cơ bản vẫn không thay đổi. Nó được phổ biến vào những năm 1960 với việc phát hành các tờ Letraset chứa các đoạn Lorem Ipsum, và gần đây hơn là với phần mềm xuất bản trên máy tính để bàn như Aldus PageMaker bao gồm các phiên bản của Lorem Ipsum.",
      "images": "https://haycafe.vn/wp-content/uploads/2021/12/hinh-anh-avatar-dep-cho-con-gai-dai-dien-Facebook-Zalo-Tiktok.jpg",
      "address": "Hà Nội",
      "createdAt": "2022-04-09T03:40:26.950Z",
      "timeofTask": "2022-04-09T03:40:26.950Z",
      "category": "Đào tạo & Giáo dục",
      "initialPrice": 423,
      "bidBy": [1],
      "requirement": [
        {
          "id": 1,
          "content": "Có sức khỏe"
        }
      ],
      "comment": null,
      "Recruiter": 3,
      "ListUser": [
        {
          "id": 5,
          "id_user": 1,
          "title": " Giúp tôi với bạn ơi !!",
          "content": "Tôi muốn bạn chỉnh lại 1 chút về thù lao của công việc, nếu được ta sẽ làm việc với nhau nhé"
        },
        {
          "id": 6,
          "id_user": 2,
          "title": " Giúp tôi với bạn ơi !!",
          "content": "Cho tôi nhận công việc này nhé !!"
        }
      ],
      "Receiver": null,
      "status": "pending"
    },
    {
      "id": 5,
      "title": "Chuyên Viên Kế Toán (Lĩnh Vực Chứng Khoán, Tài Chính, Ngân Hàng)",
      "description": " Lorem Ipsum chỉ đơn giản là văn bản giả của ngành in ấn và sắp chữ. Lorem Ipsum đã trở thành văn bản giả tiêu chuẩn của ngành kể từ những năm 1500, khi một nhà in không xác định lấy một dãy loại và xáo trộn nó để tạo thành một cuốn sách mẫu. Nó đã tồn tại không chỉ năm thế kỷ, mà còn là bước nhảy vọt trong lĩnh vực sắp chữ điện tử, về cơ bản vẫn không thay đổi. Nó được phổ biến vào những năm 1960 với việc phát hành các tờ Letraset chứa các đoạn Lorem Ipsum, và gần đây hơn là với phần mềm xuất bản trên máy tính để bàn như Aldus PageMaker bao gồm các phiên bản của Lorem Ipsum.",
      "images": "https://img2.thuthuatphanmem.vn/uploads/2018/11/30/anh-dai-dien-anime-dep_104204759.jpg",
      "address": "Hà Nội",
      "createdAt": "2022-04-09T03:40:26.950Z",
      "timeofTask": "2022-04-09T03:40:26.950Z",
      "category": "Vận chuyển",
      "initialPrice": 799,
      "bidBy": [7],
      "requirement": [
        {
          "id": 1,
          "content": "Có sức khỏe"
        },
        {
          "id": 2,
          "content": "Có trình độ"
        }
      ],
      "comment": null,
      "Recruiter": 2,
      "ListUser": null,
      "Receiver": null,
      "status": "pending"
    },
    {
      "id": 6,
      "title": "Chuyên Viên Tuyển Dụng - Hà Nội, HCM",
      "description": "Lorem Ipsum chỉ đơn giản là văn bản giả của ngành in ấn và sắp chữ. Lorem Ipsum đã trở thành văn bản giả tiêu chuẩn của ngành kể từ những năm 1500, khi một nhà in không xác định lấy một dãy loại và xáo trộn nó để tạo thành một cuốn sách mẫu. Nó đã tồn tại không chỉ năm thế kỷ, mà còn là bước nhảy vọt trong lĩnh vực sắp chữ điện tử, về cơ bản vẫn không thay đổi. Nó được phổ biến vào những năm 1960 với việc phát hành các tờ Letraset chứa các đoạn Lorem Ipsum, và gần đây hơn là với phần mềm xuất bản trên máy tính để bàn như Aldus PageMaker bao gồm các phiên bản của Lorem Ipsum.",
      "images": "https://khoinguonsangtao.vn/wp-content/uploads/2022/02/anh-dai-dien-fb-dep.jpg",
      "address": "Hà Nội",
      "createdAt": "2022-04-09T03:40:26.950Z",
      "timeofTask": "2022-04-09T03:40:26.950Z",
      "category": "Kế toán & Luật, Thuế",
      "initialPrice": 699,
      "bidBy": [2],
      "requirement": [
        {
          "id": 1,
          "content": "Có sức khỏe"
        }
      ],
      "comment": null,
      "Recruiter": 4,
      "ListUser": [
        {
          "id": 7,
          "id_user": 3,
          "title": " Giúp tôi với bạn ơi !!",
          "content": "Tôi muốn bạn chỉnh lại 1 chút về thù lao của công việc, nếu được ta sẽ làm việc với nhau nhé"
        },
        {
          "id": 8,
          "id_user": 2,
          "title": " Giúp tôi với bạn ơi !!",
          "content": "Cho tôi nhận công việc này nhé !!"
        }
      ],
      "Receiver": null,
      "status": "pending"
    },
    {
      "id": 7,
      "title": "Nhân Viên Dự Toán Nội Thất - Lương Cứng 10-20 Triệu + Thưởng",
      "description": "Lorem Ipsum chỉ đơn giản là văn bản giả của ngành in ấn và sắp chữ. Lorem Ipsum đã trở thành văn bản giả tiêu chuẩn của ngành kể từ những năm 1500, khi một nhà in không xác định lấy một dãy loại và xáo trộn nó để tạo thành một cuốn sách mẫu. Nó đã tồn tại không chỉ năm thế kỷ, mà còn là bước nhảy vọt trong lĩnh vực sắp chữ điện tử, về cơ bản vẫn không thay đổi. Nó được phổ biến vào những năm 1960 với việc phát hành các tờ Letraset chứa các đoạn Lorem Ipsum, và gần đây hơn là với phần mềm xuất bản trên máy tính để bàn như Aldus PageMaker bao gồm các phiên bản của Lorem Ipsum.",
      "images": "https://i.pinimg.com/736x/6e/af/1a/6eaf1a844ae4b6fa6eeb6ff17f468cc0.jpg",
      "address": "Hà Nội",
      "createdAt": "2022-04-09T03:40:26.950Z",
      "timeofTask": "2022-04-09T03:40:26.950Z",
      "category": "Lập trình & IT",
      "initialPrice": 300,
      "bidBy": [3],
      "requirement": [
        {
          "id": 1,
          "content": "Có sức khỏe"
        }
      ],
      "comment": null,
      "Recruiter": 1,
      "ListUser": [
        {
          "id": 9,
          "id_user": 2,
          "title": " Giúp tôi với bạn ơi !!",
          "content": "Tôi muốn bạn chỉnh lại 1 chút về thù lao của công việc, nếu được ta sẽ làm việc với nhau nhé"
        },
        {
          "id": 10,
          "id_user": 3,
          "title": "Tôi mượn bạn 3 triệu !!",
          "content": "Cho tôi nhận công việc này nhé !!"
        }
      ],
      "Receiver": null,
      "status": "working"
    }
  ]
}
